nicotv_cli/__init__.py
nicotv_cli/__version__.py
nicotv_cli/cli.py
nicotv_cli/detail.py
nicotv_cli/search.py
nicotv_cli-0.0.2.dist-info/DESCRIPTION.rst
nicotv_cli-0.0.2.dist-info/METADATA
nicotv_cli-0.0.2.dist-info/RECORD
nicotv_cli-0.0.2.dist-info/WHEEL
nicotv_cli-0.0.2.dist-info/entry_points.txt
nicotv_cli-0.0.2.dist-info/metadata.json
nicotv_cli-0.0.2.dist-info/top_level.txt
