Metadata-Version: 2.0
Name: nicotv-cli
Version: 0.0.2
Summary: 搜索动漫，然后给出下载地址
Home-page: https://github.com/hfutxqd/NicotvParser
Author: imxqd
Author-email: ahtlxqd@gmail.com
License: MIT
Platform: UNKNOWN
Classifier: License :: OSI Approved :: MIT License
Classifier: Programming Language :: Python
Classifier: Programming Language :: Python :: 3
Classifier: Programming Language :: Python :: 3.6
Classifier: Programming Language :: Python :: Implementation :: CPython
Classifier: Programming Language :: Python :: Implementation :: PyPy
Requires-Python: >=3.6.0
Requires-Dist: requests
Requires-Dist: scrapy
